vctoolkit/__init__.py
vctoolkit/io.py
vctoolkit/lbs.py
vctoolkit/math_np.py
vctoolkit/misc.py
vctoolkit/skeletons.py
vctoolkit/vis2d.py
vctoolkit/vis3d.py
vctoolkit/tf/__init__.py
vctoolkit/visgl/__init__.py
vctoolkit/viso3d/__init__.py
vctoolkit-0.1.16.0.dist-info/METADATA
vctoolkit-0.1.16.0.dist-info/WHEEL
vctoolkit-0.1.16.0.dist-info/top_level.txt
vctoolkit-0.1.16.0.dist-info/RECORD
