Metadata-Version: 2.1
Name: vctoolkit
Version: 0.1.16.0
Summary: A simple wrapper for commonly used tools in visual computing.
Home-page: https://github.com/CalciferZh/vctoolkit
Author: UNKNOWN
Author-email: yuxiao.zhou@outlook.com
License: UNKNOWN
Platform: UNKNOWN
Classifier: Programming Language :: Python :: 3
Requires-Dist: opencv-python
Requires-Dist: h5py
Requires-Dist: imageio
Requires-Dist: numpy
Requires-Dist: scipy
Requires-Dist: transforms3d
Requires-Dist: tqdm
Requires-Dist: matplotlib
Requires-Dist: pyyaml
